setup.cfg
setup.py
sequential_procedure/__init__.py
sequential_procedure/sequential_procedure.py
sequential_procedure.egg-info/PKG-INFO
sequential_procedure.egg-info/SOURCES.txt
sequential_procedure.egg-info/dependency_links.txt
sequential_procedure.egg-info/requires.txt
sequential_procedure.egg-info/top_level.txt