Metadata-Version: 1.1
Name: sequential-procedure
Version: 1.0.b1
Summary: A library that contains classes having methods that will help in estimating the sample size required for a statistical experiment. 
Home-page: https://testpypi.python.org/pypi/sequential_procedure
Author: P Jishnu Jaykumar
Author-email: jishnu.jayakumar182@gmail.com
License: UNKNOWN
Platform: UNKNOWN
Classifier: Development Status :: 3 - Alpha
Classifier: Intended Audience :: Science/Research
Classifier: Natural Language :: English
Classifier: Operating System :: OS Independent
Classifier: Programming Language :: Python :: 2.7
Classifier: Topic :: Scientific/Engineering :: Bio-Informatics
Classifier: Topic :: Scientific/Engineering :: Information Analysis
